asygpy/__init__.py
asygpy/channel.py
asygpy/notifier.py
asygpy/py.typed
asygpy-0.1.2.dist-info/LICENSE
asygpy-0.1.2.dist-info/WHEEL
asygpy-0.1.2.dist-info/METADATA
asygpy-0.1.2.dist-info/RECORD
