Metadata-Version: 2.1
Name: asygpy
Version: 0.1.2
Summary: asyncio signal handlers for Windows and Unix
License: MIT
Author: asleep-cult
Author-email: asleep.cult@gmail.com
Requires-Python: >=3.8,<4.0
Classifier: License :: OSI Approved :: MIT License
Classifier: Programming Language :: Python :: 3
Classifier: Programming Language :: Python :: 3.10
Classifier: Programming Language :: Python :: 3.8
Classifier: Programming Language :: Python :: 3.9
